skello/__init__.py
skello/__main__.py
skello/core/cli.py
skello/core/scaffold_manager.py
skello/core/models/cli_handler.py
skello/core/models/scaffold_context.py
skello/core/models/scaffolding_types.py
skello/services/dependency_handler.py
skello/services/shell_launcher.py
skello/services/venv_manager.py
skello/templates/template_manager.py
skello/templates/licenses/LICENSE_APACHE.tmpl
skello/templates/licenses/LICENSE_BSD.tmpl
skello/templates/licenses/LICENSE_GPL.tmpl
skello/templates/licenses/LICENSE_LGPL.tmpl
skello/templates/licenses/LICENSE_MIT.tmpl
skello/templates/licenses/LICENSE_MPL.tmpl
skello/templates/licenses/LICENSE_UNLICENSE.tmpl
skello/templates/project/CHANGELOG.md.tmpl
skello/templates/project/README.md.tmpl
skello/templates/project/gitignore.tmpl
skello/templates/project/main.py.tmpl
skello/templates/project/main__init__.py.tmpl
skello/templates/project/pyproject.toml.tmpl
skello/templates/project/requirements.txt.tmpl
skello/templates/project/test_main.py.tmpl
skello/utils/command_runner.py
skello/utils/directory_snapshot.py
skello/utils/directory_validator.py
skello/utils/license_helper.py
skello-2.1.4.dist-info/METADATA
skello-2.1.4.dist-info/WHEEL
skello-2.1.4.dist-info/entry_points.txt
skello-2.1.4.dist-info/licenses/LICENSE
skello-2.1.4.dist-info/RECORD
