Metadata-Version: 2.4
Name: skello
Version: 2.1.4
Summary: The friendliest way to bootstrap modern Python projects — from zero to fully-structured, ready-to-code skeleton in seconds! 🚀
Project-URL: Homepage, https://github.com/SnacktimePro/skello
Project-URL: Bug Reports, https://github.com/SnacktimePro/skello/issues
Project-URL: Source, https://github.com/SnacktimePro/skello
Project-URL: Documentation, https://github.com/SnacktimePro/skello#readme
Author-email: SnacktimePro <no-reply@example.com>
License: MIT
License-File: LICENSE
Keywords: automation,bootstrap,development,pip,project,python,skeleton,venv,virtual-environment
Classifier: Development Status :: 4 - Beta
Classifier: Intended Audience :: Developers
Classifier: Operating System :: OS Independent
Classifier: Programming Language :: Python :: 3
Classifier: Programming Language :: Python :: 3.7
Classifier: Programming Language :: Python :: 3.8
Classifier: Programming Language :: Python :: 3.9
Classifier: Programming Language :: Python :: 3.10
Classifier: Programming Language :: Python :: 3.11
Classifier: Programming Language :: Python :: 3.12
Classifier: Topic :: Software Development :: Build Tools
Classifier: Topic :: Software Development :: Libraries :: Python Modules
Classifier: Topic :: System :: Installation/Setup
Classifier: Topic :: Utilities
Requires-Python: >=3.7
Provides-Extra: dev
Requires-Dist: black>=22.0.0; extra == 'dev'
Requires-Dist: flake8>=4.0.0; extra == 'dev'
Requires-Dist: mypy>=0.900; extra == 'dev'
Requires-Dist: pytest>=6.0.0; extra == 'dev'
